README
pyvidia.py
setup.cfg
setup.py
pyvidia.egg-info/PKG-INFO
pyvidia.egg-info/SOURCES.txt
pyvidia.egg-info/dependency_links.txt
pyvidia.egg-info/entry_points.txt
pyvidia.egg-info/requires.txt
pyvidia.egg-info/top_level.txt