Metadata-Version: 1.1
Name: pyvidia
Version: 1.0.1
Summary: Nvidia driver version detector for Linux
Home-page: https://github.com/ntpeters/pyvidia
Author: Nate Peterson
Author-email: ntpeters@mtu.edu
License: MIT
Keywords: nvidia linux driver
Platform: UNKNOWN
Classifier: Development Status :: 5 - Production/Stable
Classifier: License :: OSI Approved :: MIT License
Classifier: Programming Language :: Python :: 2
Classifier: Programming Language :: Python :: 2.7
Classifier: Programming Language :: Python :: 3
Classifier: Programming Language :: Python :: 3.4
Classifier: Topic :: System :: Hardware :: Hardware Drivers
Classifier: Topic :: Utilities
